wzrdbrain/__init__.py
wzrdbrain/tricks.json
wzrdbrain/wzrdbrain.py
wzrdbrain-0.2.1.dist-info/licenses/LICENSE
wzrdbrain-0.2.1.dist-info/METADATA
wzrdbrain-0.2.1.dist-info/WHEEL
wzrdbrain-0.2.1.dist-info/top_level.txt
wzrdbrain-0.2.1.dist-info/RECORD
