Metadata-Version: 2.4
Name: wzrdbrain
Version: 0.2.1
Summary: A simple library to generate trick combinations for wizard skating.
Author: nazroll
License-Expression: Apache-2.0
Project-URL: Homepage, https://github.com/nazroll/wzrdbrain
Project-URL: Documentation, https://github.com/nazroll/wzrdbrain#readme
Project-URL: Repository, https://github.com/nazroll/wzrdbrain
Project-URL: Issues, https://github.com/nazroll/wzrdbrain/issues
Keywords: wizard skating,tricks,random,generator,inline skating
Classifier: Programming Language :: Python :: 3
Classifier: Topic :: Games/Entertainment
Classifier: Topic :: Software Development :: Libraries
Requires-Python: >=3.9
License-File: LICENSE
Requires-Dist: pydantic
Provides-Extra: dev
Requires-Dist: pytest; extra == "dev"
Requires-Dist: ruff; extra == "dev"
Requires-Dist: black; extra == "dev"
Requires-Dist: mypy; extra == "dev"
Requires-Dist: build; extra == "dev"
Requires-Dist: google-genai; extra == "dev"
Dynamic: license-file
